{
 "_meta": {
  "mission": 1,
  "game": "Syndicate (1993)",
  "sections": 4
 },
 "translations": [
  {
   "hash": "5b9247244dbec93f",
   "zh": "傭兵營區。\n\n暗殺。\n\n情報指出有一名陸軍上校正從我方武器部門\n竊取資源，並用來武裝他麾下的傭兵。\n\n他的基地就設在我方其中一座城市的外圍，\n民眾已通報他的部隊造成了不少騷亂。\n\n你的小隊將部署在營區入口附近。他們的\n任務目標是消滅這名上校。",
   "note": "default briefing"
  },
  {
   "hash": "cc3fee11449ff4ee",
   "zh": "防禦情報：\n\n監視報告顯示，營區由約五名民兵駐守，\n配備散彈槍與手槍。",
   "note": "info level 1"
  },
  {
   "hash": "3348d707e0ed886a",
   "zh": "目標情報：\n\n研判上校停留在營區最北端的建物內。一旦\n他察覺你的存在，可能會選擇撤離。絕不可\n讓他逃脫。",
   "note": "info level 2"
  },
  {
   "hash": "85fccfa8a3e01870",
   "zh": "戰術建議：\n\n單一幹員即可相當輕鬆地滲透營區並暗殺\n目標。須特別注意：散彈槍作為近距離武器\n威力驚人，但射程遠遜於手槍，因此應妥善\n安排，讓這兩種武器都能發揮最大效益。另\n建議在營區外另留一名同樣裝備的幹員待命，\n以備支援。",
   "note": "info level 3"
  }
 ]
}
